hermitcraftvideos/__init__.py
hermitcraftvideos/errors.py
hermitcraftvideos/hermit.py
hermitcraftvideos/video.py
hermitcraftvideos-0.1.1.dist-info/METADATA
hermitcraftvideos-0.1.1.dist-info/RECORD
hermitcraftvideos-0.1.1.dist-info/WHEEL
hermitcraftvideos-0.1.1.dist-info/top_level.txt
