Metadata-Version: 2.1
Name: hermitcraftvideos
Version: 0.1.1
Summary: A Wrapper for Hermicraft Video API
Home-page: https://github.com/SamHDev/Hermitcraft-Video-Api
Author: SamHDev
Author-email: samhdev@gmail.com
License: UNKNOWN
Platform: UNKNOWN
Classifier: Programming Language :: Python :: 3
Classifier: License :: OSI Approved :: MIT License
Classifier: Operating System :: OS Independent
